aiothinkingcleaner/__init__.py
aiothinkingcleaner/connection.py
aiothinkingcleaner/data.py
aiothinkingcleaner/exceptions.py
aiothinkingcleaner/thinkingcleaner.py
aiothinkingcleaner-0.1.0.dist-info/LICENSE
aiothinkingcleaner-0.1.0.dist-info/WHEEL
aiothinkingcleaner-0.1.0.dist-info/METADATA
aiothinkingcleaner-0.1.0.dist-info/RECORD
