Metadata-Version: 2.1
Name: aiothinkingcleaner
Version: 0.1.0
Summary: Library to communicate with a Thinking Cleaner module asynchronously
Home-page: https://github.com/matthijs2704/aiothinkingcleaner
License: MIT
Author: matthijs2704
Author-email: matthijs@logemann.dev
Requires-Python: >=3.7,<4.0
Classifier: Development Status :: 3 - Alpha
Classifier: Intended Audience :: Developers
Classifier: License :: OSI Approved :: MIT License
Classifier: Operating System :: OS Independent
Classifier: Programming Language :: Python :: 3
Classifier: Programming Language :: Python :: 3.10
Classifier: Programming Language :: Python :: 3.7
Classifier: Programming Language :: Python :: 3.8
Classifier: Programming Language :: Python :: 3.9
Classifier: Topic :: Software Development :: Libraries :: Python Modules
Requires-Dist: aiohttp (>=3.8.1,<4.0.0)
Requires-Dist: importlib_metadata (>=4.5.0,<5.0.0); python_version < "3.8"
Project-URL: Repository, https://github.com/matthijs2704/aiothinkingcleaner
